extra_ds_tools/__init__.py
extra_ds_tools/decorators/__init__.py
extra_ds_tools/decorators/func_decorators.py
extra_ds_tools/format.py
extra_ds_tools/ml/sklearn/meta_estimators.py
extra_ds_tools/ml/sklearn/model_selection.py
extra_ds_tools/plots/__init__.py
extra_ds_tools/plots/eda.py
extra_ds_tools/plots/format.py
extra_ds_tools/transformers/__init__.py
extra_ds_tools/transformers/numeric.py
extra_datascience_tools-0.5.0.dist-info/LICENSE
extra_datascience_tools-0.5.0.dist-info/WHEEL
extra_datascience_tools-0.5.0.dist-info/METADATA
extra_datascience_tools-0.5.0.dist-info/RECORD
