Metadata-Version: 2.1
Name: extra-datascience-tools
Version: 0.5.0
Summary: Python package which offers additional tools for data scientists.
Home-page: https://extra-datascience-tools.readthedocs.io/en/latest/index.html
License: MIT
Keywords: data science,python,plots,visualizations,decorators,ml,machine learning
Author: Tomer Gabay
Author-email: tomergabay001@gmail.com
Requires-Python: >=3.8,<4.0
Classifier: License :: OSI Approved :: MIT License
Classifier: Programming Language :: Python :: 3
Classifier: Programming Language :: Python :: 3.8
Classifier: Programming Language :: Python :: 3.9
Classifier: Programming Language :: Python :: 3.10
Requires-Dist: matplotlib (>=3.5.3,<4.0.0)
Requires-Dist: numpy (>=1.23.3,<2.0.0)
Requires-Dist: pandas (>=1.5.0,<2.0.0)
Requires-Dist: scikit-learn (>=1.1.3,<2.0.0)
Requires-Dist: scipy (>=1.7.3,<2.0.0)
Requires-Dist: seaborn (>=0.12.0,<0.13.0)
Requires-Dist: tabulate (>=0.8.10,<0.9.0)
Project-URL: Documentation, https://extra-datascience-tools.readthedocs.io/en/latest/index.html
Project-URL: Repository, https://github.com/sTomerG/extra-datascience-tools
